pybv/__init__.py
pybv/io.py
pybv-0.7.6.dist-info/METADATA
pybv-0.7.6.dist-info/WHEEL
pybv-0.7.6.dist-info/licenses/LICENSE
pybv-0.7.6.dist-info/RECORD
