Metadata-Version: 2.3
Name: pybv
Version: 0.7.6
Summary: pybv - a lightweight I/O utility for the BrainVision data format
Project-URL: Documentation, https://pybv.readthedocs.io
Project-URL: Issues, https://github.com/bids-standard/pybv/issues
Project-URL: Repository, https://github.com/bids-standard/pybv
Author: pybv developers
Maintainer-email: Stefan Appelhoff <stefan.appelhoff@mailbox.org>
License: BSD 3-Clause License
Keywords: Brain Products,BrainVision,eeg,vhdr,vmrk
Classifier: Intended Audience :: Developers
Classifier: Intended Audience :: Science/Research
Classifier: License :: OSI Approved
Classifier: Operating System :: MacOS
Classifier: Operating System :: Microsoft :: Windows
Classifier: Operating System :: POSIX :: Linux
Classifier: Programming Language :: Python
Classifier: Programming Language :: Python :: 3.9
Classifier: Programming Language :: Python :: 3.10
Classifier: Programming Language :: Python :: 3.11
Classifier: Programming Language :: Python :: 3.12
Classifier: Topic :: Scientific/Engineering
Requires-Python: >=3.9
Requires-Dist: numpy>=1.18.1
Provides-Extra: dev
Requires-Dist: build; extra == 'dev'
Requires-Dist: intersphinx-registry; extra == 'dev'
Requires-Dist: ipykernel; extra == 'dev'
Requires-Dist: ipython; extra == 'dev'
Requires-Dist: matplotlib; extra == 'dev'
Requires-Dist: mne; extra == 'dev'
Requires-Dist: numpydoc; extra == 'dev'
Requires-Dist: pre-commit; extra == 'dev'
Requires-Dist: pytest; extra == 'dev'
Requires-Dist: pytest-cov; extra == 'dev'
Requires-Dist: pytest-sugar; extra == 'dev'
Requires-Dist: ruff; extra == 'dev'
Requires-Dist: sphinx; extra == 'dev'
Requires-Dist: sphinx-copybutton; extra == 'dev'
Requires-Dist: twine; extra == 'dev'
Provides-Extra: docs
Requires-Dist: intersphinx-registry; extra == 'docs'
Requires-Dist: matplotlib; extra == 'docs'
Requires-Dist: numpydoc; extra == 'docs'
Requires-Dist: sphinx; extra == 'docs'
Requires-Dist: sphinx-copybutton; extra == 'docs'
Provides-Extra: test
Requires-Dist: build; extra == 'test'
Requires-Dist: matplotlib; extra == 'test'
Requires-Dist: mne; extra == 'test'
Requires-Dist: pre-commit; extra == 'test'
Requires-Dist: pytest; extra == 'test'
Requires-Dist: pytest-cov; extra == 'test'
Requires-Dist: pytest-sugar; extra == 'test'
Requires-Dist: ruff; extra == 'test'
Requires-Dist: twine; extra == 'test'
